haystack_integrations/components/evaluators/uptrain/__init__.py
haystack_integrations/components/evaluators/uptrain/evaluator.py
haystack_integrations/components/evaluators/uptrain/metrics.py
uptrain_haystack-0.4.1.dist-info/METADATA
uptrain_haystack-0.4.1.dist-info/WHEEL
uptrain_haystack-0.4.1.dist-info/licenses/LICENSE.txt
uptrain_haystack-0.4.1.dist-info/RECORD
