Metadata-Version: 2.1
Name: uptrain-haystack
Version: 0.4.1
Summary: An integration of UpTrain LLM evaluation framework with Haystack
Project-URL: Source, https://github.com/deepset-ai/haystack-core-integrations/tree/main/integrations/uptrain
Project-URL: Documentation, https://github.com/deepset-ai/haystack-core-integrations/blob/main/integrations/uptrain/README.md
Project-URL: Issues, https://github.com/deepset-ai/haystack-core-integrations/issues
Author-email: deepset GmbH <info@deepset.ai>
License-Expression: Apache-2.0
License-File: LICENSE.txt
Classifier: Development Status :: 4 - Beta
Classifier: Programming Language :: Python
Classifier: Programming Language :: Python :: 3.8
Classifier: Programming Language :: Python :: 3.9
Classifier: Programming Language :: Python :: 3.10
Classifier: Programming Language :: Python :: 3.11
Classifier: Programming Language :: Python :: Implementation :: CPython
Classifier: Programming Language :: Python :: Implementation :: PyPy
Requires-Python: >=3.8
Requires-Dist: haystack-ai>=2.0.0b6
Requires-Dist: litellm
Requires-Dist: nest-asyncio
Requires-Dist: uptrain==0.5.0
